Workbook

Sheet Start Here
A1: Small Business Finance Tracker
A3: Welcome! This workbook tracks one financial year of income and expenses and summarises it automatically.
A5: Quick start
A6: 1. Open "Settings" and enter your business name, a currency label (e.g. INR, USD, EUR), the month your financial year starts (1 = January ... 12 = December) and the calendar year it starts in.
A7: 2. Still on "Settings", edit the income and expense category lists to match your business (up to 20 of each). Payment methods can be edited too.
A8: 3. Delete the SAMPLE rows on "Income" and "Expenses" (see below), then record your own entries.
A9: 4. "Monthly Summary", "Category Summary" and "Dashboard" update automatically. Do not type into the shaded formula cells.
A11: IMPORTANT - sample data
A12: The 15 income rows and 15 expense rows supplied are fictional SAMPLE data (marked "SAMPLE" in the Notes / Description columns). Delete them before entering real figures.
A13: How to delete: on the Income sheet, select the sample rows inside the table, right-click and choose Delete > Table Rows. Repeat on the Expenses sheet. The table keeps its headers and formatting.
A15: Sheet guide
A16: Settings - business details, financial-year start, category lists and payment methods used by the drop-downs.
... A35: This template is an organisational tool and is not accounting or tax advice. Check figures with a qualified adviser before filing returns.

Sheet Dashboard
A1: =IF(Settings!$B$4="","Dashboard",Settings!$B$4&" - Dashboard") -> Your Business Name - Dashboard
A2: ="Amounts in "&Settings!$B$5&" - financial year" -> Amounts in INR - financial year | B2: =Settings!$B$8 -> 46113 | C2: =Settings!$B$9 -> 46477
A4: Key figures | B4: Value | C4: Detail | F4: Bar scale (largest month) | G4: =MAX(MAX('Monthly Summary'!$B$5:$B$16),MAX('Monthly Summary'!$C$5:$C$16)) -> 3750
A5: Total income | B5: ='Monthly Summary'!$B$17 -> 14456.5
A6: Total expenses | B6: ='Monthly Summary'!$C$17 -> 2181.64
A7: Net profit | B7: =B5-B6 -> 12274.86
A8: Expense ratio (expenses / income) | B8: =IF(B5=0,0,B6/B5) -> 0.15091066
A9: Profit margin (net / income) | B9: =IF(B5=0,0,B7/B5) -> 0.84908934
A10: Average monthly net | B10: =B7/12 -> 1022.905
A11: Best month (highest net) | B11: =INDEX('Monthly Summary'!$A$5:$A$16,MATCH(MAX('Monthly Summary'!$D$5:$D$16),'Monthly Summary'!$D$5:$D$16,0)) -> 46235 | C11: =MAX('Monthly Summary'!$D$5:$D$16) -> 3485.01
A12: Worst month (lowest net) | B12: =INDEX('Monthly Summary'!$A$5:$A$16,MATCH(MIN('Monthly Summary'!$D$5:$D$16),'Monthly Summary'!$D$5:$D$16,0)) -> 46327 | C12: =MIN('Monthly Summary'!$D$5:$D$16) -> 0
A13: Tax-deductible expenses (Y) | B13: =SUMIFS(Expenses!$E$5:$E$1000,Expenses!$F$5:$F$1000,"Y",Expenses!$A$5:$A$1000,">="&Settings!$B$8,Expenses!$A$5:$A$1000,"<="&Settings!$B$9) -> 2143.14
A14: Number of income entries | B14: =COUNTIFS(Income!$A$5:$A$1000,">="&Settings!$B$8,Income!$A$5:$A$1000,"<="&Settings!$B$9) -> 15
A15: Number of expense entries | B15: =COUNTIFS(Expenses!$A$5:$A$1000,">="&Settings!$B$8,Expenses!$A$5:$A$1000,"<="&Settings!$B$9) -> 15
A16: Entries dated outside this financial year | B16: =COUNTIFS(Income!$A$5:$A$1000,"<"&Settings!$B$8)+COUNTIFS(Income!$A$5:$A$1000,">"&Settings!$B$9)+COUNTIFS(Expenses!$A$5:$A$1000,"<"&Settings!$B$8)+COUNTIFS(Expenses!$A$5:$A$1000,">"&Settings!$B$9) -> 0 | C16: =IF(B16>0,"Check dates - these are excluded from all totals","All entries fall inside the year") -> All entries fall inside the year
A18: Monthly income vs expenses (bar length scaled to the largest month)
A19: Month | B19: Income | C19: Income bar | D19: Expenses | E19: Expenses bar
A20: ='Monthly Summary'!$A$5 -> 46113 | B20: ='Monthly Summary'!$B$5 -> 2450 | C20: =IF($G$4<=0,"",REPT("█",MAX(0,ROUND(B20/$G$4*30,0)))) -> ████████████████████ | D20: ='Monthly Summary'!$C$5 -> 343.99 | E20: =IF($G$4<=0,"",REPT("█",MAX(0,ROUND(D20/$G$4*30,0)))) -> ███
A21: ='Monthly Summary'!$A$6 -> 46143 | B21: ='Monthly Summary'!$B$6 -> 3095.5 | C21: =IF($G$4<=0,"",REPT("█",MAX(0,ROUND(B21/$G$4*30,0)))) -> █████████████████████████ | D21: ='Monthly Summary'!$C$6 -> 101.79 | E21: =IF($G$4<=0,"",REPT("█",MAX(0,ROUND(D21/$G$4*30,0)))) -> █
A22: ='Monthly Summary'!$A$7 -> 46174 | B22: ='Monthly Summary'!$B$7 -> 1130 | C22: =IF($G$4<=0,"",REPT("█",MAX(0,ROUND(B22/$G$4*30,0)))) -> █████████ | D22: ='Monthly Summary'!$C$7 -> 499.99 | E22: =IF($G$4<=0,"",REPT("█",MAX(0,ROUND(D22/$G$4*30,0)))) -> ████
A23: ='Monthly Summary'!$A$8 -> 46204 | B23: ='Monthly Summary'!$B$8 -> 1862.75 | C23: =IF($G$4<=0,"",REPT("█",MAX(0,ROUND(B23/$G$4*30,0)))) -> ███████████████ | D23: ='Monthly Summary'!$C$8 -> 504.99 | E23: =IF($G$4<=0,"",REPT("█",MAX(0,ROUND(D23/$G$4*30,0)))) -> ████
A24: ='Monthly Summary'!$A$9 -> 46235 | B24: ='Monthly Summary'!$B$9 -> 3750 | C24: =IF($G$4<=0,"",REPT("█",MAX(0,ROUND(B24/$G$4*30,0)))) -> ██████████████████████████████ | D24: ='Monthly Summary'!$C$9 -> 264.99 | E24: =IF($G$4<=0,"",REPT("█",MAX(0,ROUND(D24/$G$4*30,0)))) -> ██
A25: ='Monthly Summary'!$A$10 -> 46266 | B25: ='Monthly Summary'!$B$10 -> 718.25 | C25: =IF($G$4<=0,"",REPT("█",MAX(0,ROUND(B25/$G$4*30,0)))) -> ██████ | D25: ='Monthly Summary'!$C$10 -> 453.49 | E25: =IF($G$4<=0,"",REPT("█",MAX(0,ROUND(D25/$G$4*30,0)))) -> ████
A26: ='Monthly Summary'!$A$11 -> 46296 | B26: ='Monthly Summary'!$B$11 -> 1450 | C26: =IF($G$4<=0,"",REPT("█",MAX(0,ROUND(B26/$G$4*30,0)))) -> ████████████ | D26: ='Monthly Summary'!$C$11 -> 12.4 | E26: =IF($G$4<=0,"",REPT("█",MAX(0,ROUND(D26/$G$4*30,0))))
A27: ='Monthly Summary'!$A$12 -> 46327 | B27: ='Monthly Summary'!$B$12 -> 0 | C27: =IF($G$4<=0,"",REPT("█",MAX(0,ROUND(B27/$G$4*30,0)))) | D27: ='Monthly Summary'!$C$12 -> 0 | E27: =IF($G$4<=0,"",REPT("█",MAX(0,ROUND(D27/$G$4*30,0))))
A28: ='Monthly Summary'!$A$13 -> 46357 | B28: ='Monthly Summary'!$B$13 -> 0 | C28: =IF($G$4<=0,"",REPT("█",MAX(0,ROUND(B28/$G$4*30,0)))) | D28: ='Monthly Summary'!$C$13 -> 0 | E28: =IF($G$4<=0,"",REPT("█",MAX(0,ROUND(D28/$G$4*30,0))))
A29: ='Monthly Summary'!$A$14 -> 46388 | B29: ='Monthly Summary'!$B$14 -> 0 | C29: =IF($G$4<=0,"",REPT("█",MAX(0,ROUND(B29/$G$4*30,0)))) | D29: ='Monthly Summary'!$C$14 -> 0 | E29: =IF($G$4<=0,"",REPT("█",MAX(0,ROUND(D29/$G$4*30,0))))
A30: ='Monthly Summary'!$A$15 -> 46419 | B30: ='Monthly Summary'!$B$15 -> 0 | C30: =IF($G$4<=0,"",REPT("█",MAX(0,ROUND(B30/$G$4*30,0)))) | D30: ='Monthly Summary'!$C$15 -> 0 | E30: =IF($G$4<=0,"",REPT("█",MAX(0,ROUND(D30/$G$4*30,0))))
A31: ='Monthly Summary'!$A$16 -> 46447 | B31: ='Monthly Summary'!$B$16 -> 0 | C31: =IF($G$4<=0,"",REPT("█",MAX(0,ROUND(B31/$G$4*30,0)))) | D31: ='Monthly Summary'!$C$16 -> 0 | E31: =IF($G$4<=0,"",REPT("█",MAX(0,ROUND(D31/$G$4*30,0))))

Sheet Settings
A1: Settings
A2: Edit the white cells. Shaded cells are calculated.
A4: Business name | B4: Your Business Name
A5: Currency label | B5: INR
A6: Financial year start month (1-12) | B6: 4
A7: Financial year starts in (year) | B7: 2026
A8: Financial year begins | B8: =DATE(B7,B6,1) -> 46113
A9: Financial year ends | B9: =DATE(B7,B6+12,1)-1 -> 46477
A11: Up to 20 entries per list. Type over, add or clear cells - drop-downs and summaries follow.
A12: Income categories | C12: Expense categories | E12: Payment methods
A13: Client Projects | C13: Software & Subscriptions | E13: Bank transfer
A14: Retainers | C14: Equipment | E14: Card
A15: Product Sales | C15: Office & Rent | E15: Cash
A16: Consulting | C16: Travel | E16: Online payment
A17: Workshops & Training | C17: Marketing | E17: Cheque
A18: Other Income | C18: Professional Fees
C19: Insurance
C20: Bank & Payment Fees
C21: Utilities & Phone
C22: Other Expenses

Sheet Income
A1: Income
A2: SAMPLE DATA: rows 5-19 are fictional examples. Delete them (select rows > right-click > Delete > Table Rows) before entering real data.
A4: Date | B4: Client | C4: Category | D4: Description | E4: Amount | F4: Payment method | G4: Notes
A5: 46115 | B5: Maple & Finch Interiors | C5: Client Projects | D5: SAMPLE - Website redesign - deposit | E5: 1800 | F5: Bank transfer | G5: SAMPLE - delete me
A6: 46133 | B6: Brightwater Dental | C6: Retainers | D6: SAMPLE - April support retainer | E6: 650 | F6: Bank transfer | G6: SAMPLE - delete me
A7: 46148 | B7: Online shop | C7: Product Sales | D7: SAMPLE - Template sales (May batch) | E7: 245.5 | F7: Online payment | G7: SAMPLE - delete me
A8: 46161 | B8: Maple & Finch Interiors | C8: Client Projects | D8: SAMPLE - Website redesign - final balance | E8: 2200 | F8: Bank transfer | G8: SAMPLE - delete me
A9: 46163 | B9: Brightwater Dental | C9: Retainers | D9: SAMPLE - May support retainer | E9: 650 | F9: Bank transfer | G9: SAMPLE - delete me
A10: 46183 | B10: Copperleaf Cafe | C10: Consulting | D10: SAMPLE - Brand strategy workshop | E10: 480 | F10: Card | G10: SAMPLE - delete me
A11: 46195 | B11: Brightwater Dental | C11: Retainers | D11: SAMPLE - June support retainer | E11: 650 | F11: Bank transfer | G11: SAMPLE - delete me
A12: 46211 | B12: Online shop | C12: Product Sales | D12: SAMPLE - Template sales (July batch) | E12: 312.75 | F12: Online payment | G12: SAMPLE - delete me
A13: 46218 | B13: Northgate Community Library | C13: Workshops & Training | D13: SAMPLE - Digital skills session | E13: 900 | F13: Bank transfer | G13: SAMPLE - delete me
A14: 46224 | B14: Brightwater Dental | C14: Retainers | D14: SAMPLE - July support retainer | E14: 650 | F14: Bank transfer | G14: SAMPLE - delete me
A15: 46246 | B15: Fernhill Physio | C15: Client Projects | D15: SAMPLE - Booking site build | E15: 3100 | F15: Bank transfer | G15: SAMPLE - delete me
A16: 46255 | B16: Brightwater Dental | C16: Retainers | D16: SAMPLE - August support retainer | E16: 650 | F16: Bank transfer | G16: SAMPLE - delete me
... A19: 46297 | B19: Fernhill Physio | C19: Client Projects | D19: SAMPLE - Booking site - phase 2 | E19: 1450 | F19: Bank transfer | G19: SAMPLE - delete me

Sheet Expenses
A1: Expenses
A2: SAMPLE DATA: rows 5-19 are fictional examples. Delete them (select rows > right-click > Delete > Table Rows) before entering real data.
A4: Date | B4: Supplier | C4: Category | D4: Description | E4: Amount | F4: Tax deductible (Y/N)
A5: 46113 | B5: CloudDesk Software | C5: Software & Subscriptions | D5: SAMPLE - Design suite subscription | E5: 54.99 | F5: Y
A6: 46126 | B6: Pixelworks Hardware | C6: Equipment | D6: SAMPLE - External monitor | E6: 289 | F6: Y
A7: 46143 | B7: CloudDesk Software | C7: Software & Subscriptions | D7: SAMPLE - Design suite subscription | E7: 54.99 | F7: Y
A8: 46151 | B8: Regional Rail | C8: Travel | D8: SAMPLE - Client visit - return ticket | E8: 46.8 | F8: Y
A9: 46174 | B9: CloudDesk Software | C9: Software & Subscriptions | D9: SAMPLE - Design suite subscription | E9: 54.99 | F9: Y
A10: 46185 | B10: Lantern Print Studio | C10: Marketing | D10: SAMPLE - Business cards | E10: 85 | F10: Y
A11: 46203 | B11: Harbour Co-working | C11: Office & Rent | D11: SAMPLE - Desk rental (quarter) | E11: 360 | F11: Y
A12: 46204 | B12: CloudDesk Software | C12: Software & Subscriptions | D12: SAMPLE - Design suite subscription | E12: 54.99 | F12: Y
A13: 46222 | B13: Ledgerline Accountants | C13: Professional Fees | D13: SAMPLE - Year-end accounts | E13: 450 | F13: Y
A14: 46235 | B14: CloudDesk Software | C14: Software & Subscriptions | D14: SAMPLE - Design suite subscription | E14: 54.99 | F14: Y
A15: 46249 | B15: Shieldwell Insurance | C15: Insurance | D15: SAMPLE - Professional indemnity cover | E15: 210 | F15: Y
A16: 46266 | B16: CloudDesk Software | C16: Software & Subscriptions | D16: SAMPLE - Design suite subscription | E16: 54.99 | F16: Y
... A19: 46300 | B19: Merchant services provider | C19: Bank & Payment Fees | D19: SAMPLE - Card processing fees | E19: 12.4 | F19: Y

Sheet Monthly Summary
A1: Monthly Summary
A2: ="Amounts in "&Settings!$B$5&" - financial year" -> Amounts in INR - financial year | B2: =Settings!$B$8 -> 46113 | C2: =Settings!$B$9 -> 46477
A4: Month | B4: Income | C4: Expenses | D4: Net | E4: Cumulative net
A5: =DATE(Settings!$B$7,Settings!$B$6+0,1) -> 46113 | B5: =SUMIFS(Income!$E$5:$E$1000,Income!$A$5:$A$1000,">="&$A5,Income!$A$5:$A$1000,"<"&DATE(YEAR($A5),MONTH($A5)+1,1)) -> 2450 | C5: =SUMIFS(Expenses!$E$5:$E$1000,Expenses!$A$5:$A$1000,">="&$A5,Expenses!$A$5:$A$1000,"<"&DATE(YEAR($A5),MONTH($A5)+1,1)) -> 343.99 | D5: =B5-C5 -> 2106.01 | E5: =SUM($D$5:D5) -> 2106.01
A6: =DATE(Settings!$B$7,Settings!$B$6+1,1) -> 46143 | B6: =SUMIFS(Income!$E$5:$E$1000,Income!$A$5:$A$1000,">="&$A6,Income!$A$5:$A$1000,"<"&DATE(YEAR($A6),MONTH($A6)+1,1)) -> 3095.5 | C6: =SUMIFS(Expenses!$E$5:$E$1000,Expenses!$A$5:$A$1000,">="&$A6,Expenses!$A$5:$A$1000,"<"&DATE(YEAR($A6),MONTH($A6)+1,1)) -> 101.79 | D6: =B6-C6 -> 2993.71 | E6: =SUM($D$5:D6) -> 5099.72
A7: =DATE(Settings!$B$7,Settings!$B$6+2,1) -> 46174 | B7: =SUMIFS(Income!$E$5:$E$1000,Income!$A$5:$A$1000,">="&$A7,Income!$A$5:$A$1000,"<"&DATE(YEAR($A7),MONTH($A7)+1,1)) -> 1130 | C7: =SUMIFS(Expenses!$E$5:$E$1000,Expenses!$A$5:$A$1000,">="&$A7,Expenses!$A$5:$A$1000,"<"&DATE(YEAR($A7),MONTH($A7)+1,1)) -> 499.99 | D7: =B7-C7 -> 630.01 | E7: =SUM($D$5:D7) -> 5729.73
A8: =DATE(Settings!$B$7,Settings!$B$6+3,1) -> 46204 | B8: =SUMIFS(Income!$E$5:$E$1000,Income!$A$5:$A$1000,">="&$A8,Income!$A$5:$A$1000,"<"&DATE(YEAR($A8),MONTH($A8)+1,1)) -> 1862.75 | C8: =SUMIFS(Expenses!$E$5:$E$1000,Expenses!$A$5:$A$1000,">="&$A8,Expenses!$A$5:$A$1000,"<"&DATE(YEAR($A8),MONTH($A8)+1,1)) -> 504.99 | D8: =B8-C8 -> 1357.76 | E8: =SUM($D$5:D8) -> 7087.49
A9: =DATE(Settings!$B$7,Settings!$B$6+4,1) -> 46235 | B9: =SUMIFS(Income!$E$5:$E$1000,Income!$A$5:$A$1000,">="&$A9,Income!$A$5:$A$1000,"<"&DATE(YEAR($A9),MONTH($A9)+1,1)) -> 3750 | C9: =SUMIFS(Expenses!$E$5:$E$1000,Expenses!$A$5:$A$1000,">="&$A9,Expenses!$A$5:$A$1000,"<"&DATE(YEAR($A9),MONTH($A9)+1,1)) -> 264.99 | D9: =B9-C9 -> 3485.01 | E9: =SUM($D$5:D9) -> 10572.5
A10: =DATE(Settings!$B$7,Settings!$B$6+5,1) -> 46266 | B10: =SUMIFS(Income!$E$5:$E$1000,Income!$A$5:$A$1000,">="&$A10,Income!$A$5:$A$1000,"<"&DATE(YEAR($A10),MONTH($A10)+1,1)) -> 718.25 | C10: =SUMIFS(Expenses!$E$5:$E$1000,Expenses!$A$5:$A$1000,">="&$A10,Expenses!$A$5:$A$1000,"<"&DATE(YEAR($A10),MONTH($A10)+1,1)) -> 453.49 | D10: =B10-C10 -> 264.76 | E10: =SUM($D$5:D10) -> 10837.26
A11: =DATE(Settings!$B$7,Settings!$B$6+6,1) -> 46296 | B11: =SUMIFS(Income!$E$5:$E$1000,Income!$A$5:$A$1000,">="&$A11,Income!$A$5:$A$1000,"<"&DATE(YEAR($A11),MONTH($A11)+1,1)) -> 1450 | C11: =SUMIFS(Expenses!$E$5:$E$1000,Expenses!$A$5:$A$1000,">="&$A11,Expenses!$A$5:$A$1000,"<"&DATE(YEAR($A11),MONTH($A11)+1,1)) -> 12.4 | D11: =B11-C11 -> 1437.6 | E11: =SUM($D$5:D11) -> 12274.86
A12: =DATE(Settings!$B$7,Settings!$B$6+7,1) -> 46327 | B12: =SUMIFS(Income!$E$5:$E$1000,Income!$A$5:$A$1000,">="&$A12,Income!$A$5:$A$1000,"<"&DATE(YEAR($A12),MONTH($A12)+1,1)) -> 0 | C12: =SUMIFS(Expenses!$E$5:$E$1000,Expenses!$A$5:$A$1000,">="&$A12,Expenses!$A$5:$A$1000,"<"&DATE(YEAR($A12),MONTH($A12)+1,1)) -> 0 | D12: =B12-C12 -> 0 | E12: =SUM($D$5:D12) -> 12274.86
A13: =DATE(Settings!$B$7,Settings!$B$6+8,1) -> 46357 | B13: =SUMIFS(Income!$E$5:$E$1000,Income!$A$5:$A$1000,">="&$A13,Income!$A$5:$A$1000,"<"&DATE(YEAR($A13),MONTH($A13)+1,1)) -> 0 | C13: =SUMIFS(Expenses!$E$5:$E$1000,Expenses!$A$5:$A$1000,">="&$A13,Expenses!$A$5:$A$1000,"<"&DATE(YEAR($A13),MONTH($A13)+1,1)) -> 0 | D13: =B13-C13 -> 0 | E13: =SUM($D$5:D13) -> 12274.86
A14: =DATE(Settings!$B$7,Settings!$B$6+9,1) -> 46388 | B14: =SUMIFS(Income!$E$5:$E$1000,Income!$A$5:$A$1000,">="&$A14,Income!$A$5:$A$1000,"<"&DATE(YEAR($A14),MONTH($A14)+1,1)) -> 0 | C14: =SUMIFS(Expenses!$E$5:$E$1000,Expenses!$A$5:$A$1000,">="&$A14,Expenses!$A$5:$A$1000,"<"&DATE(YEAR($A14),MONTH($A14)+1,1)) -> 0 | D14: =B14-C14 -> 0 | E14: =SUM($D$5:D14) -> 12274.86
A15: =DATE(Settings!$B$7,Settings!$B$6+10,1) -> 46419 | B15: =SUMIFS(Income!$E$5:$E$1000,Income!$A$5:$A$1000,">="&$A15,Income!$A$5:$A$1000,"<"&DATE(YEAR($A15),MONTH($A15)+1,1)) -> 0 | C15: =SUMIFS(Expenses!$E$5:$E$1000,Expenses!$A$5:$A$1000,">="&$A15,Expenses!$A$5:$A$1000,"<"&DATE(YEAR($A15),MONTH($A15)+1,1)) -> 0 | D15: =B15-C15 -> 0 | E15: =SUM($D$5:D15) -> 12274.86
A16: =DATE(Settings!$B$7,Settings!$B$6+11,1) -> 46447 | B16: =SUMIFS(Income!$E$5:$E$1000,Income!$A$5:$A$1000,">="&$A16,Income!$A$5:$A$1000,"<"&DATE(YEAR($A16),MONTH($A16)+1,1)) -> 0 | C16: =SUMIFS(Expenses!$E$5:$E$1000,Expenses!$A$5:$A$1000,">="&$A16,Expenses!$A$5:$A$1000,"<"&DATE(YEAR($A16),MONTH($A16)+1,1)) -> 0 | D16: =B16-C16 -> 0 | E16: =SUM($D$5:D16) -> 12274.86
A17: Total | B17: =SUM(B5:B16) -> 14456.5 | C17: =SUM(C5:C16) -> 2181.64 | D17: =B17-C17 -> 12274.86

Sheet Category Summary
A1: Category Summary
A2: Totals within the selected financial year. Categories come from the Settings sheet.
A4: Income category | B4: Total | C4: % of income | E4: Expense category | F4: Total | G4: % of expenses
A5: =IF(Settings!$A$13="","",Settings!$A$13) -> Client Projects | B5: =IF($A5="","",SUMIFS(Income!$E$5:$E$1000,Income!$C$5:$C$1000,$A5,Income!$A$5:$A$1000,">="&Settings!$B$8,Income!$A$5:$A$1000,"<="&Settings!$B$9)) -> 8550 | C5: =IF($A5="","",IF($B$26=0,0,B5/$B$26)) -> 0.59142946 | E5: =IF(Settings!$C$13="","",Settings!$C$13) -> Software & Subscriptions | F5: =IF($E5="","",SUMIFS(Expenses!$E$5:$E$1000,Expenses!$C$5:$C$1000,$E5,Expenses!$A$5:$A$1000,">="&Settings!$B$8,Expenses!$A$5:$A$1000,"<="&Settings!$B$9)) -> 329.94 | G5: =IF($E5="","",IF($F$26=0,0,F5/$F$26)) -> 0.15123485
A6: =IF(Settings!$A$14="","",Settings!$A$14) -> Retainers | B6: =IF($A6="","",SUMIFS(Income!$E$5:$E$1000,Income!$C$5:$C$1000,$A6,Income!$A$5:$A$1000,">="&Settings!$B$8,Income!$A$5:$A$1000,"<="&Settings!$B$9)) -> 3250 | C6: =IF($A6="","",IF($B$26=0,0,B6/$B$26)) -> 0.22481237 | E6: =IF(Settings!$C$14="","",Settings!$C$14) -> Equipment | F6: =IF($E6="","",SUMIFS(Expenses!$E$5:$E$1000,Expenses!$C$5:$C$1000,$E6,Expenses!$A$5:$A$1000,">="&Settings!$B$8,Expenses!$A$5:$A$1000,"<="&Settings!$B$9)) -> 289 | G6: =IF($E6="","",IF($F$26=0,0,F6/$F$26)) -> 0.13246915
A7: =IF(Settings!$A$15="","",Settings!$A$15) -> Product Sales | B7: =IF($A7="","",SUMIFS(Income!$E$5:$E$1000,Income!$C$5:$C$1000,$A7,Income!$A$5:$A$1000,">="&Settings!$B$8,Income!$A$5:$A$1000,"<="&Settings!$B$9)) -> 756.5 | C7: =IF($A7="","",IF($B$26=0,0,B7/$B$26)) -> 0.052329402 | E7: =IF(Settings!$C$15="","",Settings!$C$15) -> Office & Rent | F7: =IF($E7="","",SUMIFS(Expenses!$E$5:$E$1000,Expenses!$C$5:$C$1000,$E7,Expenses!$A$5:$A$1000,">="&Settings!$B$8,Expenses!$A$5:$A$1000,"<="&Settings!$B$9)) -> 720 | G7: =IF($E7="","",IF($F$26=0,0,F7/$F$26)) -> 0.33002695
A8: =IF(Settings!$A$16="","",Settings!$A$16) -> Consulting | B8: =IF($A8="","",SUMIFS(Income!$E$5:$E$1000,Income!$C$5:$C$1000,$A8,Income!$A$5:$A$1000,">="&Settings!$B$8,Income!$A$5:$A$1000,"<="&Settings!$B$9)) -> 1000 | C8: =IF($A8="","",IF($B$26=0,0,B8/$B$26)) -> 0.069173036 | E8: =IF(Settings!$C$16="","",Settings!$C$16) -> Travel | F8: =IF($E8="","",SUMIFS(Expenses!$E$5:$E$1000,Expenses!$C$5:$C$1000,$E8,Expenses!$A$5:$A$1000,">="&Settings!$B$8,Expenses!$A$5:$A$1000,"<="&Settings!$B$9)) -> 46.8 | G8: =IF($E8="","",IF($F$26=0,0,F8/$F$26)) -> 0.021451752
A9: =IF(Settings!$A$17="","",Settings!$A$17) -> Workshops & Training | B9: =IF($A9="","",SUMIFS(Income!$E$5:$E$1000,Income!$C$5:$C$1000,$A9,Income!$A$5:$A$1000,">="&Settings!$B$8,Income!$A$5:$A$1000,"<="&Settings!$B$9)) -> 900 | C9: =IF($A9="","",IF($B$26=0,0,B9/$B$26)) -> 0.062255733 | E9: =IF(Settings!$C$17="","",Settings!$C$17) -> Marketing | F9: =IF($E9="","",SUMIFS(Expenses!$E$5:$E$1000,Expenses!$C$5:$C$1000,$E9,Expenses!$A$5:$A$1000,">="&Settings!$B$8,Expenses!$A$5:$A$1000,"<="&Settings!$B$9)) -> 85 | G9: =IF($E9="","",IF($F$26=0,0,F9/$F$26)) -> 0.038961515
A10: =IF(Settings!$A$18="","",Settings!$A$18) -> Other Income | B10: =IF($A10="","",SUMIFS(Income!$E$5:$E$1000,Income!$C$5:$C$1000,$A10,Income!$A$5:$A$1000,">="&Settings!$B$8,Income!$A$5:$A$1000,"<="&Settings!$B$9)) -> 0 | C10: =IF($A10="","",IF($B$26=0,0,B10/$B$26)) -> 0 | E10: =IF(Settings!$C$18="","",Settings!$C$18) -> Professional Fees | F10: =IF($E10="","",SUMIFS(Expenses!$E$5:$E$1000,Expenses!$C$5:$C$1000,$E10,Expenses!$A$5:$A$1000,">="&Settings!$B$8,Expenses!$A$5:$A$1000,"<="&Settings!$B$9)) -> 450 | G10: =IF($E10="","",IF($F$26=0,0,F10/$F$26)) -> 0.20626685
A11: =IF(Settings!$A$19="","",Settings!$A$19) | B11: =IF($A11="","",SUMIFS(Income!$E$5:$E$1000,Income!$C$5:$C$1000,$A11,Income!$A$5:$A$1000,">="&Settings!$B$8,Income!$A$5:$A$1000,"<="&Settings!$B$9)) | C11: =IF($A11="","",IF($B$26=0,0,B11/$B$26)) | E11: =IF(Settings!$C$19="","",Settings!$C$19) -> Insurance | F11: =IF($E11="","",SUMIFS(Expenses!$E$5:$E$1000,Expenses!$C$5:$C$1000,$E11,Expenses!$A$5:$A$1000,">="&Settings!$B$8,Expenses!$A$5:$A$1000,"<="&Settings!$B$9)) -> 210 | G11: =IF($E11="","",IF($F$26=0,0,F11/$F$26)) -> 0.096257861
A12: =IF(Settings!$A$20="","",Settings!$A$20) | B12: =IF($A12="","",SUMIFS(Income!$E$5:$E$1000,Income!$C$5:$C$1000,$A12,Income!$A$5:$A$1000,">="&Settings!$B$8,Income!$A$5:$A$1000,"<="&Settings!$B$9)) | C12: =IF($A12="","",IF($B$26=0,0,B12/$B$26)) | E12: =IF(Settings!$C$20="","",Settings!$C$20) -> Bank & Payment Fees | F12: =IF($E12="","",SUMIFS(Expenses!$E$5:$E$1000,Expenses!$C$5:$C$1000,$E12,Expenses!$A$5:$A$1000,">="&Settings!$B$8,Expenses!$A$5:$A$1000,"<="&Settings!$B$9)) -> 12.4 | G12: =IF($E12="","",IF($F$26=0,0,F12/$F$26)) -> 0.0056837975
A13: =IF(Settings!$A$21="","",Settings!$A$21) | B13: =IF($A13="","",SUMIFS(Income!$E$5:$E$1000,Income!$C$5:$C$1000,$A13,Income!$A$5:$A$1000,">="&Settings!$B$8,Income!$A$5:$A$1000,"<="&Settings!$B$9)) | C13: =IF($A13="","",IF($B$26=0,0,B13/$B$26)) | E13: =IF(Settings!$C$21="","",Settings!$C$21) -> Utilities & Phone | F13: =IF($E13="","",SUMIFS(Expenses!$E$5:$E$1000,Expenses!$C$5:$C$1000,$E13,Expenses!$A$5:$A$1000,">="&Settings!$B$8,Expenses!$A$5:$A$1000,"<="&Settings!$B$9)) -> 0 | G13: =IF($E13="","",IF($F$26=0,0,F13/$F$26)) -> 0
A14: =IF(Settings!$A$22="","",Settings!$A$22) | B14: =IF($A14="","",SUMIFS(Income!$E$5:$E$1000,Income!$C$5:$C$1000,$A14,Income!$A$5:$A$1000,">="&Settings!$B$8,Income!$A$5:$A$1000,"<="&Settings!$B$9)) | C14: =IF($A14="","",IF($B$26=0,0,B14/$B$26)) | E14: =IF(Settings!$C$22="","",Settings!$C$22) -> Other Expenses | F14: =IF($E14="","",SUMIFS(Expenses!$E$5:$E$1000,Expenses!$C$5:$C$1000,$E14,Expenses!$A$5:$A$1000,">="&Settings!$B$8,Expenses!$A$5:$A$1000,"<="&Settings!$B$9)) -> 38.5 | G14: =IF($E14="","",IF($F$26=0,0,F14/$F$26)) -> 0.017647275
A15: =IF(Settings!$A$23="","",Settings!$A$23) | B15: =IF($A15="","",SUMIFS(Income!$E$5:$E$1000,Income!$C$5:$C$1000,$A15,Income!$A$5:$A$1000,">="&Settings!$B$8,Income!$A$5:$A$1000,"<="&Settings!$B$9)) | C15: =IF($A15="","",IF($B$26=0,0,B15/$B$26)) | E15: =IF(Settings!$C$23="","",Settings!$C$23) | F15: =IF($E15="","",SUMIFS(Expenses!$E$5:$E$1000,Expenses!$C$5:$C$1000,$E15,Expenses!$A$5:$A$1000,">="&Settings!$B$8,Expenses!$A$5:$A$1000,"<="&Settings!$B$9)) | G15: =IF($E15="","",IF($F$26=0,0,F15/$F$26))
A16: =IF(Settings!$A$24="","",Settings!$A$24) | B16: =IF($A16="","",SUMIFS(Income!$E$5:$E$1000,Income!$C$5:$C$1000,$A16,Income!$A$5:$A$1000,">="&Settings!$B$8,Income!$A$5:$A$1000,"<="&Settings!$B$9)) | C16: =IF($A16="","",IF($B$26=0,0,B16/$B$26)) | E16: =IF(Settings!$C$24="","",Settings!$C$24) | F16: =IF($E16="","",SUMIFS(Expenses!$E$5:$E$1000,Expenses!$C$5:$C$1000,$E16,Expenses!$A$5:$A$1000,">="&Settings!$B$8,Expenses!$A$5:$A$1000,"<="&Settings!$B$9)) | G16: =IF($E16="","",IF($F$26=0,0,F16/$F$26))
A17: =IF(Settings!$A$25="","",Settings!$A$25) | B17: =IF($A17="","",SUMIFS(Income!$E$5:$E$1000,Income!$C$5:$C$1000,$A17,Income!$A$5:$A$1000,">="&Settings!$B$8,Income!$A$5:$A$1000,"<="&Settings!$B$9)) | C17: =IF($A17="","",IF($B$26=0,0,B17/$B$26)) | E17: =IF(Settings!$C$25="","",Settings!$C$25) | F17: =IF($E17="","",SUMIFS(Expenses!$E$5:$E$1000,Expenses!$C$5:$C$1000,$E17,Expenses!$A$5:$A$1000,">="&Settings!$B$8,Expenses!$A$5:$A$1000,"<="&Settings!$B$9)) | G17: =IF($E17="","",IF($F$26=0,0,F17/$F$26))
A18: =IF(Settings!$A$26="","",Settings!$A$26) | B18: =IF($A18="","",SUMIFS(Income!$E$5:$E$1000,Income!$C$5:$C$1000,$A18,Income!$A$5:$A$1000,">="&Settings!$B$8,Income!$A$5:$A$1000,"<="&Settings!$B$9)) | C18: =IF($A18="","",IF($B$26=0,0,B18/$B$26)) | E18: =IF(Settings!$C$26="","",Settings!$C$26) | F18: =IF($E18="","",SUMIFS(Expenses!$E$5:$E$1000,Expenses!$C$5:$C$1000,$E18,Expenses!$A$5:$A$1000,">="&Settings!$B$8,Expenses!$A$5:$A$1000,"<="&Settings!$B$9)) | G18: =IF($E18="","",IF($F$26=0,0,F18/$F$26))
A19: =IF(Settings!$A$27="","",Settings!$A$27) | B19: =IF($A19="","",SUMIFS(Income!$E$5:$E$1000,Income!$C$5:$C$1000,$A19,Income!$A$5:$A$1000,">="&Settings!$B$8,Income!$A$5:$A$1000,"<="&Settings!$B$9)) | C19: =IF($A19="","",IF($B$26=0,0,B19/$B$26)) | E19: =IF(Settings!$C$27="","",Settings!$C$27) | F19: =IF($E19="","",SUMIFS(Expenses!$E$5:$E$1000,Expenses!$C$5:$C$1000,$E19,Expenses!$A$5:$A$1000,">="&Settings!$B$8,Expenses!$A$5:$A$1000,"<="&Settings!$B$9)) | G19: =IF($E19="","",IF($F$26=0,0,F19/$F$26))
A20: =IF(Settings!$A$28="","",Settings!$A$28) | B20: =IF($A20="","",SUMIFS(Income!$E$5:$E$1000,Income!$C$5:$C$1000,$A20,Income!$A$5:$A$1000,">="&Settings!$B$8,Income!$A$5:$A$1000,"<="&Settings!$B$9)) | C20: =IF($A20="","",IF($B$26=0,0,B20/$B$26)) | E20: =IF(Settings!$C$28="","",Settings!$C$28) | F20: =IF($E20="","",SUMIFS(Expenses!$E$5:$E$1000,Expenses!$C$5:$C$1000,$E20,Expenses!$A$5:$A$1000,">="&Settings!$B$8,Expenses!$A$5:$A$1000,"<="&Settings!$B$9)) | G20: =IF($E20="","",IF($F$26=0,0,F20/$F$26))
A21: =IF(Settings!$A$29="","",Settings!$A$29) | B21: =IF($A21="","",SUMIFS(Income!$E$5:$E$1000,Income!$C$5:$C$1000,$A21,Income!$A$5:$A$1000,">="&Settings!$B$8,Income!$A$5:$A$1000,"<="&Settings!$B$9)) | C21: =IF($A21="","",IF($B$26=0,0,B21/$B$26)) | E21: =IF(Settings!$C$29="","",Settings!$C$29) | F21: =IF($E21="","",SUMIFS(Expenses!$E$5:$E$1000,Expenses!$C$5:$C$1000,$E21,Expenses!$A$5:$A$1000,">="&Settings!$B$8,Expenses!$A$5:$A$1000,"<="&Settings!$B$9)) | G21: =IF($E21="","",IF($F$26=0,0,F21/$F$26))
A22: =IF(Settings!$A$30="","",Settings!$A$30) | B22: =IF($A22="","",SUMIFS(Income!$E$5:$E$1000,Income!$C$5:$C$1000,$A22,Income!$A$5:$A$1000,">="&Settings!$B$8,Income!$A$5:$A$1000,"<="&Settings!$B$9)) | C22: =IF($A22="","",IF($B$26=0,0,B22/$B$26)) | E22: =IF(Settings!$C$30="","",Settings!$C$30) | F22: =IF($E22="","",SUMIFS(Expenses!$E$5:$E$1000,Expenses!$C$5:$C$1000,$E22,Expenses!$A$5:$A$1000,">="&Settings!$B$8,Expenses!$A$5:$A$1000,"<="&Settings!$B$9)) | G22: =IF($E22="","",IF($F$26=0,0,F22/$F$26))
A23: =IF(Settings!$A$31="","",Settings!$A$31) | B23: =IF($A23="","",SUMIFS(Income!$E$5:$E$1000,Income!$C$5:$C$1000,$A23,Income!$A$5:$A$1000,">="&Settings!$B$8,Income!$A$5:$A$1000,"<="&Settings!$B$9)) | C23: =IF($A23="","",IF($B$26=0,0,B23/$B$26)) | E23: =IF(Settings!$C$31="","",Settings!$C$31) | F23: =IF($E23="","",SUMIFS(Expenses!$E$5:$E$1000,Expenses!$C$5:$C$1000,$E23,Expenses!$A$5:$A$1000,">="&Settings!$B$8,Expenses!$A$5:$A$1000,"<="&Settings!$B$9)) | G23: =IF($E23="","",IF($F$26=0,0,F23/$F$26))
A24: =IF(Settings!$A$32="","",Settings!$A$32) | B24: =IF($A24="","",SUMIFS(Income!$E$5:$E$1000,Income!$C$5:$C$1000,$A24,Income!$A$5:$A$1000,">="&Settings!$B$8,Income!$A$5:$A$1000,"<="&Settings!$B$9)) | C24: =IF($A24="","",IF($B$26=0,0,B24/$B$26)) | E24: =IF(Settings!$C$32="","",Settings!$C$32) | F24: =IF($E24="","",SUMIFS(Expenses!$E$5:$E$1000,Expenses!$C$5:$C$1000,$E24,Expenses!$A$5:$A$1000,">="&Settings!$B$8,Expenses!$A$5:$A$1000,"<="&Settings!$B$9)) | G24: =IF($E24="","",IF($F$26=0,0,F24/$F$26))
A25: Uncategorised / other | B25: =B26-SUM(B5:B24) -> 0 | C25: =IF($B$26=0,0,B25/$B$26) -> 0 | E25: Uncategorised / other | F25: =F26-SUM(F5:F24) -> 0 | G25: =IF($F$26=0,0,F25/$F$26) -> 0
A26: Total income | B26: =SUMIFS(Income!$E$5:$E$1000,Income!$A$5:$A$1000,">="&Settings!$B$8,Income!$A$5:$A$1000,"<="&Settings!$B$9) -> 14456.5 | C26: =IF($B$26=0,0,1) -> 1 | E26: Total expenses | F26: =SUMIFS(Expenses!$E$5:$E$1000,Expenses!$A$5:$A$1000,">="&Settings!$B$8,Expenses!$A$5:$A$1000,"<="&Settings!$B$9) -> 2181.64 | G26: =IF($F$26=0,0,1) -> 1
